CHANGES.txt
MANIFEST.in
README.rst
setup.cfg
setup.py
s3authbasic/__init__.py
s3authbasic/runapp.py
s3authbasic/s3controller.py
s3authbasic/testing.py
s3authbasic/views.py
s3authbasic.egg-info/PKG-INFO
s3authbasic.egg-info/SOURCES.txt
s3authbasic.egg-info/dependency_links.txt
s3authbasic.egg-info/entry_points.txt
s3authbasic.egg-info/not-zip-safe
s3authbasic.egg-info/requires.txt
s3authbasic.egg-info/top_level.txt
s3authbasic/config-templates/development.ini
s3authbasic/config-templates/production.ini
s3authbasic/tests/__init__.py
s3authbasic/tests/test_authbasic.py
s3authbasic/tests/test_runapp.py
s3authbasic/tests/test_settings.py
s3authbasic/tests/test_views.py
s3authbasic/tests/fixtures/bucket_example/example.jpeg
s3authbasic/tests/fixtures/bucket_example/index.html
s3authbasic/tests/fixtures/bucket_example/blue child/index.html
s3authbasic/tests/fixtures/bucket_example/level1/index.html
s3authbasic/tests/fixtures/bucket_example/level1/other.html
s3authbasic/tests/fixtures/bucket_example/level1/level2/index.html