Metadata-Version: 1.1
Name: s3authbasic
Version: 0.1.2
Summary: s3authbasic
Home-page: http://www.ant30.es/
Author: Antonio Perez-Aranda Alcaide
Author-email: ant30tx@gmail.com
License: UNKNOWN
Download-URL: https://github.com/ant30/s3authbasic/tarball/0.1.2
Keywords: web pyramid pylons s3
Platform: UNKNOWN
Classifier: Programming Language :: Python
Classifier: Framework :: Pyramid
Classifier: Topic :: Internet :: WWW/HTTP
Classifier: Topic :: Internet :: WWW/HTTP :: WSGI :: Application
